build_magic/__init__.py
build_magic/__main__.py
build_magic/actions.py
build_magic/cli.py
build_magic/core.py
build_magic/exc.py
build_magic/macro.py
build_magic/output.py
build_magic/reference.py
build_magic/runner.py
build_magic/static/build-magic_template.yaml
build_magic/static/config_schema.json
build_magic-0.5.1.dist-info/LICENSE
build_magic-0.5.1.dist-info/METADATA
build_magic-0.5.1.dist-info/WHEEL
build_magic-0.5.1.dist-info/entry_points.txt
build_magic-0.5.1.dist-info/top_level.txt
build_magic-0.5.1.dist-info/RECORD
