Metadata-Version: 2.1
Name: build-magic
Version: 0.5.1
Summary: A general purpose build/install/deploy tool.
Home-page: https://cmmorrow.github.io/build-magic/
Author: Chris Morrow
Author-email: cmmorrow@gmail.com
License: MIT
Project-URL: Documentation, https://cmmorrow.github.io/build-magic/
Project-URL: Source, https://github.com/cmmorrow/build-magic
Project-URL: Bug Tracker, https://github.com/cmmorrow/build-magic/issues
Platform: UNKNOWN
Requires-Python: !=2.*, !=3.0.*, !=3.1.*, !=3.2.*, !=3.3.*, !=3.4.*, !=3.5.*, >=3.6
Requires-Dist: cffi (==1.14.6)
Requires-Dist: click (==8.0.3)
Requires-Dist: colorama (==0.4.4)
Requires-Dist: cryptography (==36.0.1)
Requires-Dist: jsonschema (==3.2.0)
Requires-Dist: docker (==5.0.3)
Requires-Dist: nltk (==3.6.7)
Requires-Dist: paramiko (==2.10.1)
Requires-Dist: python-vagrant (==0.5.15)
Requires-Dist: PyYAML (==6.0)
Requires-Dist: scp (==0.14.2)
Requires-Dist: yaspin (==2.1.0)
